levdoom/__init__.py
levdoom/envs/__init__.py
levdoom/envs/base.py
levdoom/envs/defend_the_center/__init__.py
levdoom/envs/defend_the_center/conf.cfg
levdoom/envs/defend_the_center/scenario.py
levdoom/envs/defend_the_center/maps/complete.wad
levdoom/envs/defend_the_center/maps/default.wad
levdoom/envs/defend_the_center/maps/fast_enemies.wad
levdoom/envs/defend_the_center/maps/fast_flying_enemies.wad
levdoom/envs/defend_the_center/maps/fast_resized_enemies_gore.wad
levdoom/envs/defend_the_center/maps/flying_enemies.wad
levdoom/envs/defend_the_center/maps/fuzzy_enemies.wad
levdoom/envs/defend_the_center/maps/fuzzy_enemies_gore.wad
levdoom/envs/defend_the_center/maps/gore.wad
levdoom/envs/defend_the_center/maps/gore_mossy_bricks.wad
levdoom/envs/defend_the_center/maps/gore_stone_wall_fuzzy_enemies.wad
levdoom/envs/defend_the_center/maps/mossy_bricks.wad
levdoom/envs/defend_the_center/maps/resized_enemies.wad
levdoom/envs/defend_the_center/maps/resized_flying_enemies_mossy_bricks.wad
levdoom/envs/defend_the_center/maps/resized_fuzzy_enemies.wad
levdoom/envs/defend_the_center/maps/stone_wall.wad
levdoom/envs/defend_the_center/maps/stone_wall_flying_enemies.wad
levdoom/envs/dodge_projectiles/__init__.py
levdoom/envs/dodge_projectiles/conf.cfg
levdoom/envs/dodge_projectiles/scenario.py
levdoom/envs/dodge_projectiles/maps/arachnotron.wad
levdoom/envs/dodge_projectiles/maps/barons.wad
levdoom/envs/dodge_projectiles/maps/barons_flaming_skulls.wad
levdoom/envs/dodge_projectiles/maps/cacodemons.wad
levdoom/envs/dodge_projectiles/maps/cacodemons_flames.wad
levdoom/envs/dodge_projectiles/maps/city.wad
levdoom/envs/dodge_projectiles/maps/city_arachnotron.wad
levdoom/envs/dodge_projectiles/maps/city_resized_agent.wad
levdoom/envs/dodge_projectiles/maps/close_enemies.wad
levdoom/envs/dodge_projectiles/maps/complete.wad
levdoom/envs/dodge_projectiles/maps/default.wad
levdoom/envs/dodge_projectiles/maps/flames.wad
levdoom/envs/dodge_projectiles/maps/flames_flaming_skulls_mancubus.wad
levdoom-1.0.2.dist-info/licenses/LICENSE.txt
levdoom-1.0.2.dist-info/METADATA
levdoom-1.0.2.dist-info/WHEEL
levdoom-1.0.2.dist-info/top_level.txt
levdoom-1.0.2.dist-info/RECORD
