Metadata-Version: 2.4
Name: LevDoom
Version: 1.0.2
Summary: LevDoom: A Generalization Benchmark for Deep Reinforcement Learning
Author-email: Tristan Tomilin <tristan.tomilin@hotmail.com>
License: MIT
Project-URL: Homepage, https://github.com/TTomilin/LevDoom
Project-URL: Issues, https://github.com/TTomilin/LevDoom/issues
Keywords: vizdoom,reinforcement learning,benchmarking,generalization
Classifier: Programming Language :: Python :: 3
Classifier: License :: OSI Approved :: MIT License
Classifier: Operating System :: OS Independent
Requires-Python: >=3.8
License-File: LICENSE.txt
Requires-Dist: vizdoom
Requires-Dist: scipy
Requires-Dist: opencv-python
Requires-Dist: gymnasium>=0.28
Provides-Extra: rl
Requires-Dist: tianshou; extra == "rl"
Requires-Dist: wandb; extra == "rl"
Dynamic: license-file
